vdsolverf/__init__.py
vdsolverf/emses/__init__.py
vdsolverf/emses/tmpolary_input.py
vdsolverf/emses/wrapper.py
vdist_solver_fortran-0.1.0.dist-info/LICENSE
vdist_solver_fortran-0.1.0.dist-info/METADATA
vdist_solver_fortran-0.1.0.dist-info/WHEEL
vdist_solver_fortran-0.1.0.dist-info/top_level.txt
vdist_solver_fortran-0.1.0.dist-info/RECORD
