Metadata-Version: 2.1
Name: vdist-solver-fortran
Version: 0.1.0
Summary: Wrapper of velocsty distribution solver written in Fortran
Author-email: Nkzono99 <j-nakazono@stu.kobe-u.ac.jp>
Maintainer-email: Nkzono99 <j-nakazono@stu.kobe-u.ac.jp>
License: Apache License
Project-URL: Repository, https://github.com/Nkzono99/vdist-solver-fortran.git
Classifier: License :: OSI Approved :: Apache Software License
Classifier: Development Status :: 3 - Alpha
Classifier: Programming Language :: Python :: 3
Classifier: Programming Language :: Python :: 3.7
Classifier: Programming Language :: Python :: 3.8
Classifier: Programming Language :: Python :: 3.9
Requires-Python: >=3.7
License-File: LICENSE
Requires-Dist: f90nml
Requires-Dist: vdist-solver
Requires-Dist: emout
Requires-Dist: numpy
